{
  "collectionName": "components_ui_section_with_images",
  "info": {
    "displayName": "Section With Image",
    "icon": "network-wired",
    "description": ""
  },
  "options": {},
  "attributes": {
    "title": {
      "type": "string"
    },
    "image": {
      "type": "media",
      "multiple": false,
      "required": false,
      "allowedTypes": [
        "images",
        "files",
        "videos",
        "audios"
      ]
    },
    "paragraphs": {
      "type": "component",
      "repeatable": true,
      "component": "ui.text"
    }
  }
}
